CHANGES.md
LICENSE.txt
MANIFEST.in
README.md
setup.cfg
setup.py
muscima/__init__.py
muscima/cropobject.py
muscima/cropobject_class.py
muscima/dataset.py
muscima/grammar.py
muscima/graph.py
muscima/inference.py
muscima/inference_engine_constants.py
muscima/io.py
muscima/stafflines.py
muscima/utils.py
muscima.egg-info/PKG-INFO
muscima.egg-info/SOURCES.txt
muscima.egg-info/dependency_links.txt
muscima.egg-info/requires.txt
muscima.egg-info/top_level.txt
scripts/add_staff_relationships.py
scripts/add_staffline_symbols.py
scripts/analyze_agreement.py
scripts/analyze_annotations.py
scripts/analyze_tracking_log.py
scripts/get_images_from_muscima.py
scripts/strip_staffline_symbols.py
test/test_cropobject.py