Metadata-Version: 1.1
Name: muscima
Version: 0.10.0
Summary: Tools for the MUSCIMA++ dataset of music notation.
Home-page: https://muscima.readthedocs.io
Author: Jan Hajič jr.
Author-email: hajicj@ufal.mff.cuni.cz
License: MIT Software License
Platform: a
Platform: n
Platform: y
Classifier: Programming Language :: Python
Classifier: Development Status :: 4 - Beta
Classifier: Natural Language :: English
Classifier: Environment :: Web Environment
Classifier: Intended Audience :: Science/Research
Classifier: License :: OSI Approved :: MIT License
Classifier: Operating System :: OS Independent
Classifier: Topic :: Scientific/Engineering :: Interface Engine/Protocol Translator
